odoo/addons/purchase_order_downpayment/README.rst
odoo/addons/purchase_order_downpayment/__init__.py
odoo/addons/purchase_order_downpayment/__manifest__.py
odoo/addons/purchase_order_downpayment/i18n/es.po
odoo/addons/purchase_order_downpayment/i18n/it.po
odoo/addons/purchase_order_downpayment/i18n/purchase_order_downpayment.pot
odoo/addons/purchase_order_downpayment/i18n/sv.po
odoo/addons/purchase_order_downpayment/models/__init__.py
odoo/addons/purchase_order_downpayment/models/account_payment.py
odoo/addons/purchase_order_downpayment/models/purchase_order.py
odoo/addons/purchase_order_downpayment/readme/CONTRIBUTORS.rst
odoo/addons/purchase_order_downpayment/readme/DESCRIPTION.rst
odoo/addons/purchase_order_downpayment/security/ir.model.access.csv
odoo/addons/purchase_order_downpayment/static/description/icon.png
odoo/addons/purchase_order_downpayment/static/description/index.html
odoo/addons/purchase_order_downpayment/tests/__init__.py
odoo/addons/purchase_order_downpayment/tests/test_purchase_order_downpayment.py
odoo/addons/purchase_order_downpayment/views/purchase_view.xml
odoo/addons/purchase_order_downpayment/wizard/__init__.py
odoo/addons/purchase_order_downpayment/wizard/purchase_order_downpayment_wiz_view.xml
odoo/addons/purchase_order_downpayment/wizard/purchase_order_downpayment_wizard.py
odoo_addon_purchase_order_downpayment-16.0.1.0.0.7.dist-info/METADATA
odoo_addon_purchase_order_downpayment-16.0.1.0.0.7.dist-info/WHEEL
odoo_addon_purchase_order_downpayment-16.0.1.0.0.7.dist-info/top_level.txt
odoo_addon_purchase_order_downpayment-16.0.1.0.0.7.dist-info/RECORD
